{"imgname": "JX_165_7_9", "imgsize": {"width": 1910, "height": 3106}, "blocks": [{"x": 17, "y": 439, "w": 1746, "h": 2524, "char_id": "org0"}], "columns": [{"x": 17, "y": 439, "w": 192, "h": 2524}, {"x": 209, "y": 439, "w": 157, "h": 2524}, {"x": 366, "y": 439, "w": 154, "h": 2524}, {"x": 520, "y": 439, "w": 156, "h": 2524}, {"x": 676, "y": 439, "w": 168, "h": 2524}, {"x": 1012, "y": 439, "w": 118, "h": 2524}, {"x": 1149, "y": 439, "w": 153, "h": 2524}, {"x": 1302, "y": 439, "w": 151, "h": 2524}, {"x": 1453, "y": 439, "w": 154, "h": 2524}, {"x": 1607, "y": 439, "w": 156, "h": 2524}]}