{
  "imgname": "GL_1049_1_10",
  "imgsize": {
    "width": 6000,
    "height": 3900
  },
  "blocks": [
    {
      "x": 48,
      "y": 850,
      "w": 5825.5,
      "h": 2437,
      "no": 1,
      "cc": 1,
      "block_id": "b1"
    }
  ],
  "columns": [
    {
      "x": 5476,
      "y": 0,
      "w": 210.1,
      "h": 3900,
      "cc": 1,
      "txt": "善",
      "no": 1,
      "column_id": "b1c1",
      "char_id": "b1c1",
      "block_no": 1,
      "line_no": 1,
      "char_no": null,
      "changed": true
    },
    {
      "x": 5192,
      "y": 0,
      "w": 284,
      "h": 3900,
      "cc": 1,
      "txt": "六世祖名懿師摩",
      "no": 2,
      "column_id": "b1c2",
      "char_id": "b1c2",
      "block_no": 1,
      "line_no": 2,
      "char_no": null
    },
    {
      "x": 4964,
      "y": 0,
      "w": 228,
      "h": 3900,
      "cc": 1,
      "txt": "五世祖名憂羅陁",
      "no": 3,
      "column_id": "b1c3",
      "char_id": "b1c3",
      "block_no": 1,
      "line_no": 3,
      "char_no": null
    },
    {
      "x": 4703,
      "y": 0,
      "w": 261,
      "h": 3900,
      "cc": 1,
      "txt": "第四世高祖名瞿羅",
      "no": 4,
      "column_id": "b1c4",
      "char_id": "b1c4",
      "block_no": 1,
      "line_no": 4,
      "char_no": null
    },
    {
      "x": 4490,
      "y": 0,
      "w": 213,
      "h": 3900,
      "cc": 1,
      "txt": "三世曾祖名足浮羅",
      "no": 5,
      "column_id": "b1c5",
      "char_id": "b1c5",
      "block_no": 1,
      "line_no": 5,
      "char_no": null
    },
    {
      "x": 4249,
      "y": 0,
      "w": 241,
      "h": 3900,
      "cc": 1,
      "txt": "二世祖名師子類",
      "no": 6,
      "column_id": "b1c6",
      "char_id": "b1c6",
      "block_no": 1,
      "line_no": 6,
      "char_no": null
    },
    {
      "x": 3991,
      "y": 0,
      "w": 258,
      "h": 3900,
      "cc": 1,
      "txt": "一世菩薩父名淨飯",
      "no": 7,
      "column_id": "b1c7",
      "char_id": "b1c7",
      "block_no": 1,
      "line_no": 7,
      "char_no": null
    },
    {
      "x": 3733,
      "y": 0,
      "w": 258,
      "h": 3900,
      "cc": 1,
      "txt": "金輪名菩薩悉達",
      "no": 8,
      "column_id": "b1c8",
      "char_id": "b1c8",
      "block_no": 1,
      "line_no": 8,
      "char_no": null
    },
    {
      "x": 3486,
      "y": 0,
      "w": 247,
      "h": 3900,
      "cc": 1,
      "txt": "鐵輪王名羅睺羅",
      "no": 9,
      "column_id": "b1c9",
      "char_id": "b1c9",
      "block_no": 1,
      "line_no": 9,
      "char_no": null
    },
    {
      "x": 3245,
      "y": 0,
      "w": 241,
      "h": 3900,
      "cc": 1,
      "txt": "已前依撿爰初宇宙造化我成肇建",
      "no": 10,
      "column_id": "b1c10",
      "char_id": "b1c10",
      "block_no": 1,
      "line_no": 10,
      "char_no": null
    },
    {
      "x": 3001,
      "y": 0,
      "w": 244,
      "h": 3900,
      "cc": 1,
      "txt": "皇統維群品源民主迄于善思",
      "no": 11,
      "column_id": "b1c11",
      "char_id": "b1c11",
      "block_no": 1,
      "line_no": 11,
      "char_no": null
    },
    {
      "x": 2763,
      "y": 0,
      "w": 238,
      "h": 3900,
      "cc": 1,
      "txt": "參相承三十三世沿斯已後十代",
      "no": 12,
      "column_id": "b1c12",
      "char_id": "b1c12",
      "block_no": 1,
      "line_no": 12,
      "char_no": null
    },
    {
      "x": 2526,
      "y": 0,
      "w": 237,
      "h": 3900,
      "cc": 1,
      "txt": "勃興竝是聖王俱稱帝種同胤則可",
      "no": 13,
      "column_id": "b1c13",
      "char_id": "b1c13",
      "block_no": 1,
      "line_no": 13,
      "char_no": null
    },
    {
      "x": 2258,
      "y": 0,
      "w": 268,
      "h": 3900,
      "cc": 1,
      "txt": "從正異緖或是支離莫不受天明一",
      "no": 14,
      "column_id": "b1c14",
      "char_id": "b1c14",
      "block_no": 1,
      "line_no": 14,
      "char_no": null
    },
    {
      "x": 2044,
      "y": 0,
      "w": 214,
      "h": 3900,
      "cc": 1,
      "txt": "命君臨難以測知至",
      "no": 15,
      "column_id": "b1c15",
      "char_id": "b1c15",
      "block_no": 1,
      "line_no": 15,
      "char_no": null
    },
    {
      "x": 1810,
      "y": 0,
      "w": 234,
      "h": 3900,
      "cc": 1,
      "txt": "雨漢諸帝非者多魏晉宋齊武",
      "no": 16,
      "column_id": "b1c16",
      "char_id": "b1c16",
      "block_no": 1,
      "line_no": 16,
      "char_no": null
    },
    {
      "x": 1576,
      "y": 0,
      "w": 234,
      "h": 3900,
      "cc": 1,
      "txt": "斯例彼理固然",
      "no": 17,
      "column_id": "b1c17",
      "char_id": "b1c17",
      "block_no": 1,
      "line_no": 17,
      "char_no": null
    },
    {
      "x": 1298,
      "y": 0,
      "w": 278,
      "h": 3900,
      "cc": 1,
      "txt": "今從初擧數凡八萬四千二百五十三",
      "no": 18,
      "column_id": "b1c18",
      "char_id": "b1c18",
      "block_no": 1,
      "line_no": 18,
      "char_no": null
    },
    {
      "x": 1027,
      "y": 0,
      "w": 271,
      "h": 3900,
      "cc": 1,
      "txt": "王後至於菩薩",
      "no": 19,
      "column_id": "b1c19",
      "char_id": "b1c19",
      "block_no": 1,
      "line_no": 19,
      "char_no": null
    },
    {
      "x": 783,
      "y": 0,
      "w": 244,
      "h": 3900,
      "cc": 1,
      "txt": "None",
      "no": 20,
      "column_id": "b1c20",
      "char_id": "b1c20",
      "block_no": 1,
      "line_no": 20,
      "char_no": null
    },
    {
      "x": 549,
      "y": 0,
      "w": 234,
      "h": 3900,
      "cc": 1,
      "txt": "菩薩祖師子類王有四子",
      "no": 21,
      "column_id": "b1c21",
      "char_id": "b1c21",
      "block_no": 1,
      "line_no": 21,
      "char_no": null
    },
    {
      "x": 291,
      "y": 0,
      "w": 258,
      "h": 3900,
      "cc": 1,
      "txt": "一名淨飯自飯",
      "no": 22,
      "column_id": "b1c22",
      "char_id": "b1c22",
      "block_no": 1,
      "line_no": 22,
      "char_no": null
    },
    {
      "x": 3,
      "y": 0,
      "w": 288,
      "h": 3900,
      "cc": 1,
      "txt": "三名斛敀四名露",
      "no": 23,
      "column_id": "b1c23",
      "char_id": "b1c23",
      "block_no": 1,
      "line_no": 23,
      "char_no": null
    },
    {
      "char_id": "new1",
      "x": 5708.7,
      "y": 1106.8,
      "w": 180.6,
      "h": 1438.8
    }
  ],
  "chars": [
    {
      "x": 5494,
      "y": 932,
      "w": 192,
      "h": 144,
      "cc": 0.8277,
      "no": 2,
      "char_id": "b1c1c2",
      "changed": true
    },
    {
      "x": 5502,
      "y": 1105,
      "w": 174,
      "h": 176,
      "cc": 0.9689,
      "no": 5,
      "char_id": "b1c1c5",
      "changed": true
    },
    {
      "x": 5694,
      "y": 1252,
      "w": 141,
      "h": 105,
      "cc": 0.7652,
      "no": 6,
      "char_id": "b1c1c6",
      "changed": true
    },
    {
      "x": 5501,
      "y": 1291,
      "w": 164,
      "h": 127,
      "cc": 0.8219,
      "no": 7,
      "char_id": "b1c1c7",
      "changed": true
    },
    {
      "x": 5713,
      "y": 1362,
      "w": 113,
      "h": 95,
      "cc": 0.977,
      "no": 8,
      "char_id": "b1c1c8",
      "changed": true
    },
    {
      "x": 5497,
      "y": 1427,
      "w": 186,
      "h": 158,
      "cc": 0.9925,
      "no": 9,
      "char_id": "b1c1c9",
      "changed": true
    },
    {
      "x": 5730,
      "y": 1464,
      "w": 90,
      "h": 86,
      "cc": 0.7878,
      "no": 10,
      "char_id": "b1c1c10",
      "changed": true
    },
    {
      "x": 5713,
      "y": 1555,
      "w": 111,
      "h": 110,
      "cc": 0.9574,
      "no": 11,
      "char_id": "b1c1c11",
      "changed": true
    },
    {
      "x": 5505,
      "y": 1586,
      "w": 173,
      "h": 166,
      "cc": 0.9779,
      "no": 12,
      "char_id": "b1c1c12",
      "changed": true
    },
    {
      "x": 5526,
      "y": 1762,
      "w": 146,
      "h": 167,
      "cc": 0.9819,
      "no": 13,
      "char_id": "b1c1c13",
      "changed": true
    },
    {
      "x": 5711,
      "y": 1822,
      "w": 105,
      "h": 123,
      "cc": 0.9227,
      "no": 14,
      "char_id": "b1c1c14",
      "changed": true
    },
    {
      "x": 5493,
      "y": 1946,
      "w": 200,
      "h": 168.9,
      "cc": 0.8874,
      "no": 15,
      "char_id": "b1c1c15",
      "changed": true
    },
    {
      "x": 5719,
      "y": 1949,
      "w": 87,
      "h": 72,
      "cc": 0.8229,
      "no": 16,
      "char_id": "b1c1c16",
      "changed": true
    },
    {
      "x": 5721,
      "y": 2025,
      "w": 103,
      "h": 102,
      "cc": 0.8888,
      "no": 18,
      "char_id": "b1c1c18",
      "changed": true
    },
    {
      "x": 5689,
      "y": 2287,
      "w": 148,
      "h": 166,
      "cc": 0.7955,
      "no": 19,
      "char_id": "b1c1c19",
      "changed": true
    },
    {
      "x": 5235,
      "y": 910,
      "w": 168,
      "h": 197,
      "cc": 0.9096,
      "no": 1,
      "char_id": "b1c2c1",
      "changed": true
    },
    {
      "x": 5231,
      "y": 1118,
      "w": 190,
      "h": 128,
      "cc": 0.6387,
      "no": 2,
      "char_id": "b1c2c2",
      "changed": true
    },
    {
      "x": 5245,
      "y": 1259,
      "w": 174,
      "h": 120,
      "cc": 0.9437,
      "no": 3,
      "char_id": "b1c2c3",
      "changed": true
    },
    {
      "x": 5225,
      "y": 1432,
      "w": 208,
      "h": 134,
      "cc": 0.9753,
      "no": 4,
      "char_id": "b1c2c4",
      "changed": true
    },
    {
      "x": 5231,
      "y": 1597,
      "w": 161,
      "h": 150,
      "cc": 0.972,
      "no": 5,
      "char_id": "b1c2c5",
      "changed": true
    },
    {
      "x": 5242,
      "y": 1772,
      "w": 195,
      "h": 163,
      "cc": 0.8039,
      "no": 6,
      "char_id": "b1c2c6",
      "changed": true
    },
    {
      "x": 5253,
      "y": 1973,
      "w": 156,
      "h": 151,
      "cc": 0.9344,
      "no": 7,
      "char_id": "b1c2c7",
      "changed": true
    },
    {
      "x": 5224,
      "y": 2127,
      "w": 190,
      "h": 211,
      "cc": 0.916,
      "no": 8,
      "char_id": "b1c2c8",
      "changed": true
    },
    {
      "x": 5204,
      "y": 2360,
      "w": 112,
      "h": 131,
      "cc": 0.621,
      "no": 9,
      "char_id": "b1c2c9",
      "changed": true
    },
    {
      "x": 5336,
      "y": 2485,
      "w": 96,
      "h": 85,
      "cc": 0.8937,
      "no": 10,
      "char_id": "b1c2c10"
    },
    {
      "x": 5209,
      "y": 2506,
      "w": 115,
      "h": 128,
      "cc": 0.9622,
      "no": 11,
      "char_id": "b1c2c11",
      "changed": true
    },
    {
      "x": 5325,
      "y": 2584,
      "w": 103,
      "h": 122,
      "cc": 0.8931,
      "no": 12,
      "char_id": "b1c2c12",
      "changed": true
    },
    {
      "x": 4982,
      "y": 899,
      "w": 173,
      "h": 199,
      "cc": 0.8902,
      "no": 1,
      "char_id": "b1c3c1",
      "changed": true
    },
    {
      "x": 4983,
      "y": 1109,
      "w": 179,
      "h": 128,
      "cc": 0.9524,
      "no": 2,
      "char_id": "b1c3c2",
      "changed": true
    },
    {
      "x": 4989,
      "y": 1251,
      "w": 172,
      "h": 119,
      "cc": 0.9042,
      "no": 3,
      "char_id": "b1c3c3",
      "changed": true
    },
    {
      "x": 4984,
      "y": 1412,
      "w": 195,
      "h": 151,
      "cc": 0.8018,
      "no": 4,
      "char_id": "b1c3c4",
      "changed": true
    },
    {
      "x": 5010,
      "y": 1593,
      "w": 134,
      "h": 131,
      "cc": 0.7333,
      "no": 5,
      "char_id": "b1c3c5",
      "changed": true
    },
    {
      "x": 4999,
      "y": 1753,
      "w": 183,
      "h": 202,
      "cc": 0.9499,
      "no": 6,
      "char_id": "b1c3c6",
      "changed": true
    },
    {
      "x": 4995,
      "y": 1969,
      "w": 175,
      "h": 177,
      "cc": 0.753,
      "no": 7,
      "char_id": "b1c3c7",
      "changed": true
    },
    {
      "x": 4998,
      "y": 2173,
      "w": 171,
      "h": 155,
      "cc": 0.7046,
      "no": 8,
      "char_id": "b1c3c8",
      "changed": true
    },
    {
      "x": 5078,
      "y": 2375,
      "w": 117,
      "h": 107,
      "cc": 0.8167,
      "no": 9,
      "char_id": "b1c3c9",
      "changed": true
    },
    {
      "x": 5060,
      "y": 2500,
      "w": 116,
      "h": 134,
      "cc": 0.7043,
      "no": 10,
      "char_id": "b1c3c10",
      "changed": true
    },
    {
      "x": 4758,
      "y": 901.1,
      "w": 157,
      "h": 203.9,
      "cc": 0.8313,
      "no": 1,
      "char_id": "b1c4c1",
      "changed": true
    },
    {
      "x": 4770,
      "y": 1131,
      "w": 140,
      "h": 90,
      "cc": 0.8265,
      "no": 2,
      "char_id": "b1c4c2"
    },
    {
      "x": 4761,
      "y": 1254,
      "w": 167,
      "h": 127,
      "cc": 0.9416,
      "no": 3,
      "char_id": "b1c4c3",
      "changed": true
    },
    {
      "x": 4770,
      "y": 1427,
      "w": 149,
      "h": 188,
      "cc": 0.9669,
      "no": 4,
      "char_id": "b1c4c4",
      "changed": true
    },
    {
      "x": 4754,
      "y": 1644,
      "w": 183,
      "h": 152,
      "cc": 0.9692,
      "no": 5,
      "char_id": "b1c4c5",
      "changed": true
    },
    {
      "x": 4770,
      "y": 1821,
      "w": 146,
      "h": 141,
      "cc": 0.8232,
      "no": 6,
      "char_id": "b1c4c6",
      "changed": true
    },
    {
      "x": 4771,
      "y": 1989,
      "w": 141,
      "h": 187,
      "cc": 0.854,
      "no": 7,
      "char_id": "b1c4c7",
      "changed": true
    },
    {
      "x": 4755,
      "y": 2205,
      "w": 167,
      "h": 176,
      "cc": 0.8598,
      "no": 8,
      "char_id": "b1c4c8",
      "changed": true
    },
    {
      "x": 4835,
      "y": 2417,
      "w": 84,
      "h": 107,
      "cc": 0.9226,
      "no": 9,
      "char_id": "b1c4c9",
      "changed": true
    },
    {
      "x": 4732,
      "y": 2439,
      "w": 99,
      "h": 119,
      "cc": 0.9643,
      "no": 10,
      "char_id": "b1c4c10",
      "changed": true
    },
    {
      "x": 4833,
      "y": 2538,
      "w": 89,
      "h": 97,
      "cc": 0.9393,
      "no": 11,
      "char_id": "b1c4c11",
      "changed": true
    },
    {
      "x": 4509,
      "y": 918,
      "w": 173,
      "h": 190.9,
      "cc": 0.7082,
      "no": 1,
      "char_id": "b1c5c1",
      "changed": true
    },
    {
      "x": 4517,
      "y": 1139,
      "w": 172,
      "h": 114,
      "cc": 0.9343,
      "no": 2,
      "char_id": "b1c5c2",
      "changed": true
    },
    {
      "x": 4506,
      "y": 1284,
      "w": 179,
      "h": 122,
      "cc": 0.8763,
      "no": 3,
      "char_id": "b1c5c3",
      "changed": true
    },
    {
      "x": 4532,
      "y": 1428,
      "w": 135,
      "h": 180,
      "cc": 0.7662,
      "no": 4,
      "char_id": "b1c5c4"
    },
    {
      "x": 4506,
      "y": 1623,
      "w": 196,
      "h": 155,
      "cc": 0.7877,
      "no": 5,
      "char_id": "b1c5c5",
      "changed": true
    },
    {
      "x": 4522,
      "y": 1797,
      "w": 146,
      "h": 150,
      "cc": 0.6859,
      "no": 6,
      "char_id": "b1c5c6"
    },
    {
      "x": 4521,
      "y": 1967,
      "w": 165,
      "h": 143,
      "cc": 0.9279,
      "no": 7,
      "char_id": "b1c5c7",
      "changed": true
    },
    {
      "x": 4525,
      "y": 2118,
      "w": 163,
      "h": 174,
      "cc": 0.8104,
      "no": 8,
      "char_id": "b1c5c8",
      "changed": true
    },
    {
      "x": 4515,
      "y": 2315,
      "w": 172,
      "h": 172,
      "cc": 0.7807,
      "no": 9,
      "char_id": "b1c5c9",
      "changed": true
    },
    {
      "x": 4267,
      "y": 901,
      "w": 178,
      "h": 203.9,
      "cc": 0.7831,
      "no": 1,
      "char_id": "b1c6c1",
      "changed": true
    },
    {
      "x": 4269,
      "y": 1140,
      "w": 167,
      "h": 90,
      "cc": 0.843,
      "no": 3,
      "char_id": "b1c6c3",
      "changed": true
    },
    {
      "x": 4259,
      "y": 1269,
      "w": 185,
      "h": 130,
      "cc": 0.9935,
      "no": 4,
      "char_id": "b1c6c4",
      "changed": true
    },
    {
      "x": 4258,
      "y": 1454,
      "w": 201,
      "h": 154,
      "cc": 0.9893,
      "no": 5,
      "char_id": "b1c6c5",
      "changed": true
    },
    {
      "x": 4264,
      "y": 1615,
      "w": 176,
      "h": 139,
      "cc": 0.9693,
      "no": 6,
      "char_id": "b1c6c6"
    },
    {
      "x": 4290,
      "y": 1793,
      "w": 166,
      "h": 162,
      "cc": 0.9213,
      "no": 7,
      "char_id": "b1c6c7",
      "changed": true
    },
    {
      "x": 4295,
      "y": 1985,
      "w": 157,
      "h": 160,
      "cc": 0.6591,
      "no": 8,
      "char_id": "b1c6c8",
      "changed": true
    },
    {
      "x": 4275,
      "y": 2148,
      "w": 177,
      "h": 154,
      "cc": 0.9249,
      "no": 9,
      "char_id": "b1c6c9",
      "changed": true
    },
    {
      "x": 4012,
      "y": 899.1,
      "w": 179,
      "h": 195.9,
      "cc": 0.924,
      "no": 1,
      "char_id": "b1c7c1",
      "changed": true
    },
    {
      "x": 4016,
      "y": 1142,
      "w": 182,
      "h": 45,
      "cc": 0.8039,
      "no": 2,
      "char_id": "b1c7c2"
    },
    {
      "x": 4013,
      "y": 1261,
      "w": 188,
      "h": 124,
      "cc": 0.9882,
      "no": 3,
      "char_id": "b1c7c3",
      "changed": true
    },
    {
      "x": 4008,
      "y": 1408,
      "w": 202,
      "h": 166,
      "cc": 0.9687,
      "no": 4,
      "char_id": "b1c7c4",
      "changed": true
    },
    {
      "x": 4023,
      "y": 1580,
      "w": 193,
      "h": 184,
      "cc": 0.9486,
      "no": 5,
      "char_id": "b1c7c5",
      "changed": true
    },
    {
      "x": 4024,
      "y": 1770,
      "w": 198,
      "h": 143,
      "cc": 0.7398,
      "no": 6,
      "char_id": "b1c7c6",
      "changed": true
    },
    {
      "x": 4010,
      "y": 1921,
      "w": 175,
      "h": 147,
      "cc": 0.9651,
      "no": 7,
      "char_id": "b1c7c7"
    },
    {
      "x": 4031,
      "y": 2083,
      "w": 169,
      "h": 193,
      "cc": 0.7559,
      "no": 8,
      "char_id": "b1c7c8",
      "changed": true
    },
    {
      "x": 4008,
      "y": 2297,
      "w": 242,
      "h": 171,
      "cc": 0.8897,
      "no": 9,
      "char_id": "b1c7c9",
      "changed": true
    },
    {
      "x": 4105,
      "y": 2475,
      "w": 140,
      "h": 115,
      "cc": 0.8581,
      "no": 10,
      "char_id": "b1c7c10",
      "changed": true
    },
    {
      "x": 4014,
      "y": 2485,
      "w": 87,
      "h": 91,
      "cc": 0.8036,
      "no": 11,
      "char_id": "b1c7c11",
      "changed": true
    },
    {
      "x": 4004,
      "y": 2591,
      "w": 120,
      "h": 106,
      "cc": 0.9408,
      "no": 12,
      "char_id": "b1c7c12",
      "changed": true
    },
    {
      "x": 4124,
      "y": 2592,
      "w": 114,
      "h": 118,
      "cc": 0.9638,
      "no": 13,
      "char_id": "b1c7c13",
      "changed": true
    },
    {
      "x": 4014,
      "y": 2704,
      "w": 99,
      "h": 110,
      "cc": 0.9466,
      "no": 14,
      "char_id": "b1c7c14",
      "changed": true
    },
    {
      "x": 4118,
      "y": 2711,
      "w": 135,
      "h": 108,
      "cc": 0.9705,
      "no": 15,
      "char_id": "b1c7c15",
      "changed": true
    },
    {
      "x": 4015,
      "y": 2820,
      "w": 82,
      "h": 96,
      "cc": 0.845,
      "no": 16,
      "char_id": "b1c7c16"
    },
    {
      "x": 4110,
      "y": 2823,
      "w": 122,
      "h": 112,
      "cc": 0.9005,
      "no": 17,
      "char_id": "b1c7c17",
      "changed": true
    },
    {
      "x": 3999,
      "y": 2936,
      "w": 122,
      "h": 103,
      "cc": 0.9061,
      "no": 18,
      "char_id": "b1c7c18",
      "changed": true
    },
    {
      "x": 4123,
      "y": 2940,
      "w": 93,
      "h": 96,
      "cc": 0.9195,
      "no": 19,
      "char_id": "b1c7c19",
      "changed": true
    },
    {
      "x": 4002,
      "y": 3040,
      "w": 123,
      "h": 99,
      "cc": 0.9573,
      "no": 20,
      "char_id": "b1c7c20",
      "changed": true
    },
    {
      "x": 4127,
      "y": 3050,
      "w": 83,
      "h": 93,
      "cc": 0.8999,
      "no": 21,
      "char_id": "b1c7c21",
      "changed": true
    },
    {
      "x": 4005,
      "y": 3139,
      "w": 116,
      "h": 124,
      "cc": 0.9311,
      "no": 22,
      "char_id": "b1c7c22"
    },
    {
      "x": 4125,
      "y": 3155,
      "w": 102,
      "h": 113,
      "cc": 0.9443,
      "no": 23,
      "char_id": "b1c7c23",
      "changed": true
    },
    {
      "x": 3765,
      "y": 900,
      "w": 202,
      "h": 166,
      "cc": 0.7693,
      "no": 1,
      "char_id": "b1c8c1",
      "changed": true
    },
    {
      "x": 3765,
      "y": 1074,
      "w": 204,
      "h": 163,
      "cc": 0.6994,
      "no": 2,
      "char_id": "b1c8c2",
      "changed": true
    },
    {
      "x": 3770,
      "y": 1250,
      "w": 182,
      "h": 112,
      "cc": 0.6448,
      "no": 3,
      "char_id": "b1c8c3",
      "changed": true
    },
    {
      "x": 3755,
      "y": 1375,
      "w": 171,
      "h": 155,
      "cc": 0.9734,
      "no": 4,
      "char_id": "b1c8c4",
      "changed": true
    },
    {
      "x": 3766,
      "y": 1540,
      "w": 188,
      "h": 167,
      "cc": 0.839,
      "no": 5,
      "char_id": "b1c8c5",
      "changed": true
    },
    {
      "x": 3772,
      "y": 1717,
      "w": 187,
      "h": 179,
      "cc": 0.8846,
      "no": 6,
      "char_id": "b1c8c6",
      "changed": true
    },
    {
      "x": 3781,
      "y": 1895,
      "w": 173,
      "h": 165,
      "cc": 0.7637,
      "no": 7,
      "char_id": "b1c8c7",
      "changed": true
    },
    {
      "x": 3754,
      "y": 2070,
      "w": 210,
      "h": 176,
      "cc": 0.9563,
      "no": 8,
      "char_id": "b1c8c8",
      "changed": true
    },
    {
      "x": 3491,
      "y": 878,
      "w": 219,
      "h": 171,
      "cc": 0.9809,
      "no": 1,
      "char_id": "b1c9c1",
      "changed": true
    },
    {
      "x": 3491,
      "y": 1049,
      "w": 222,
      "h": 167,
      "cc": 0.9242,
      "no": 2,
      "char_id": "b1c9c2",
      "changed": true
    },
    {
      "x": 3512,
      "y": 1244,
      "w": 151,
      "h": 119,
      "cc": 0.8747,
      "no": 3,
      "char_id": "b1c9c3"
    },
    {
      "x": 3504,
      "y": 1385,
      "w": 166,
      "h": 148,
      "cc": 0.9728,
      "no": 4,
      "char_id": "b1c9c4",
      "changed": true
    },
    {
      "x": 3532,
      "y": 1563,
      "w": 171,
      "h": 168,
      "cc": 0.8537,
      "no": 5,
      "char_id": "b1c9c5",
      "changed": true
    },
    {
      "x": 3519,
      "y": 1756,
      "w": 213,
      "h": 163,
      "cc": 0.8615,
      "no": 6,
      "char_id": "b1c9c6",
      "changed": true
    },
    {
      "x": 3516,
      "y": 1943,
      "w": 188,
      "h": 158,
      "cc": 0.7033,
      "no": 7,
      "char_id": "b1c9c7"
    },
    {
      "x": 3292,
      "y": 896,
      "w": 132,
      "h": 134,
      "cc": 0.9542,
      "no": 1,
      "char_id": "b1c10c1",
      "changed": true
    },
    {
      "x": 3267,
      "y": 1041,
      "w": 171,
      "h": 176.9,
      "cc": 0.9761,
      "no": 2,
      "char_id": "b1c10c2",
      "changed": true
    },
    {
      "x": 3265,
      "y": 1219,
      "w": 208,
      "h": 144,
      "cc": 0.8296,
      "no": 3,
      "char_id": "b1c10c3",
      "changed": true
    },
    {
      "x": 3260,
      "y": 1372,
      "w": 213,
      "h": 164,
      "cc": 0.9244,
      "no": 4,
      "char_id": "b1c10c4",
      "changed": true
    },
    {
      "x": 3292,
      "y": 1544,
      "w": 161,
      "h": 186,
      "cc": 0.8995,
      "no": 5,
      "char_id": "b1c10c5",
      "changed": true
    },
    {
      "x": 3249,
      "y": 1739,
      "w": 190,
      "h": 154,
      "cc": 0.991,
      "no": 6,
      "char_id": "b1c10c6"
    },
    {
      "x": 3275,
      "y": 1903,
      "w": 157,
      "h": 170,
      "cc": 0.982,
      "no": 7,
      "char_id": "b1c10c7",
      "changed": true
    },
    {
      "x": 3278,
      "y": 2085,
      "w": 160,
      "h": 135,
      "cc": 0.9607,
      "no": 8,
      "char_id": "b1c10c8",
      "changed": true
    },
    {
      "x": 3260,
      "y": 2234,
      "w": 202,
      "h": 179,
      "cc": 0.9372,
      "no": 9,
      "char_id": "b1c10c9",
      "changed": true
    },
    {
      "x": 3270,
      "y": 2421,
      "w": 187,
      "h": 147,
      "cc": 0.9185,
      "no": 10,
      "char_id": "b1c10c10",
      "changed": true
    },
    {
      "x": 3264,
      "y": 2582,
      "w": 205,
      "h": 172,
      "cc": 0.6747,
      "no": 11,
      "char_id": "b1c10c11",
      "changed": true
    },
    {
      "x": 3286,
      "y": 2756,
      "w": 178,
      "h": 156,
      "cc": 0.868,
      "no": 12,
      "char_id": "b1c10c12",
      "changed": true
    },
    {
      "x": 3265,
      "y": 2914,
      "w": 201,
      "h": 173,
      "cc": 0.9316,
      "no": 13,
      "char_id": "b1c10c13",
      "changed": true
    },
    {
      "x": 3248,
      "y": 3090,
      "w": 232,
      "h": 179,
      "cc": 0.8502,
      "no": 14,
      "char_id": "b1c10c14",
      "changed": true
    },
    {
      "x": 3016,
      "y": 891.1,
      "w": 167,
      "h": 191.9,
      "cc": 0.8106,
      "no": 2,
      "char_id": "b1c11c2",
      "changed": true
    },
    {
      "x": 2992,
      "y": 1086,
      "w": 230,
      "h": 143,
      "cc": 0.9874,
      "no": 3,
      "char_id": "b1c11c3",
      "changed": true
    },
    {
      "x": 3010,
      "y": 1239,
      "w": 203,
      "h": 158,
      "cc": 0.9939,
      "no": 4,
      "char_id": "b1c11c4",
      "changed": true
    },
    {
      "x": 3008,
      "y": 1405,
      "w": 189,
      "h": 151,
      "cc": 0.8764,
      "no": 5,
      "char_id": "b1c11c5"
    },
    {
      "x": 3006,
      "y": 1566,
      "w": 207,
      "h": 154,
      "cc": 0.9927,
      "no": 6,
      "char_id": "b1c11c6",
      "changed": true
    },
    {
      "x": 3025,
      "y": 1720,
      "w": 159,
      "h": 128,
      "cc": 0.9705,
      "no": 7,
      "char_id": "b1c11c7",
      "changed": true
    },
    {
      "x": 3007,
      "y": 1871,
      "w": 222,
      "h": 173,
      "cc": 0.7798,
      "no": 8,
      "char_id": "b1c11c8",
      "changed": true
    },
    {
      "x": 3014,
      "y": 2058,
      "w": 180,
      "h": 168,
      "cc": 0.9928,
      "no": 9,
      "char_id": "b1c11c9",
      "changed": true
    },
    {
      "x": 3030,
      "y": 2235,
      "w": 166,
      "h": 150,
      "cc": 0.94,
      "no": 10,
      "char_id": "b1c11c10",
      "changed": true
    },
    {
      "x": 3018,
      "y": 2401,
      "w": 181,
      "h": 152,
      "cc": 0.9602,
      "no": 11,
      "char_id": "b1c11c11",
      "changed": true
    },
    {
      "x": 3004,
      "y": 2570,
      "w": 214,
      "h": 160,
      "cc": 0.9895,
      "no": 12,
      "char_id": "b1c11c12",
      "changed": true
    },
    {
      "x": 3025,
      "y": 2748,
      "w": 175,
      "h": 155,
      "cc": 0.985,
      "no": 13,
      "char_id": "b1c11c13",
      "changed": true
    },
    {
      "x": 3014,
      "y": 2912,
      "w": 193,
      "h": 166,
      "cc": 0.9907,
      "no": 14,
      "char_id": "b1c11c14",
      "changed": true
    },
    {
      "x": 3029,
      "y": 3097,
      "w": 180,
      "h": 145,
      "cc": 0.9623,
      "no": 15,
      "char_id": "b1c11c15",
      "changed": true
    },
    {
      "x": 2795,
      "y": 885,
      "w": 161,
      "h": 177,
      "cc": 0.9012,
      "no": 1,
      "char_id": "b1c12c1",
      "changed": true
    },
    {
      "x": 2790,
      "y": 1064,
      "w": 202,
      "h": 168,
      "cc": 0.9227,
      "no": 2,
      "char_id": "b1c12c2",
      "changed": true
    },
    {
      "x": 2791,
      "y": 1247,
      "w": 177,
      "h": 149,
      "cc": 0.6863,
      "no": 3,
      "char_id": "b1c12c3",
      "changed": true
    },
    {
      "x": 2802,
      "y": 1421,
      "w": 202,
      "h": 150,
      "cc": 0.9783,
      "no": 4,
      "char_id": "b1c12c4",
      "changed": true
    },
    {
      "x": 2796,
      "y": 1597,
      "w": 193,
      "h": 121,
      "cc": 0.8352,
      "no": 5,
      "char_id": "b1c12c5",
      "changed": true
    },
    {
      "x": 2804,
      "y": 1742,
      "w": 168,
      "h": 135,
      "cc": 0.9373,
      "no": 6,
      "char_id": "b1c12c6",
      "changed": true
    },
    {
      "x": 2800,
      "y": 1903,
      "w": 183,
      "h": 115,
      "cc": 0.8981,
      "no": 7,
      "char_id": "b1c12c7",
      "changed": true
    },
    {
      "x": 2788,
      "y": 2068,
      "w": 196,
      "h": 131,
      "cc": 0.772,
      "no": 8,
      "char_id": "b1c12c8"
    },
    {
      "x": 2799,
      "y": 2251,
      "w": 189,
      "h": 159,
      "cc": 0.9736,
      "no": 9,
      "char_id": "b1c12c9",
      "changed": true
    },
    {
      "x": 2784,
      "y": 2441,
      "w": 221,
      "h": 170,
      "cc": 0.9765,
      "no": 10,
      "char_id": "b1c12c10",
      "changed": true
    },
    {
      "x": 2842,
      "y": 2639,
      "w": 146,
      "h": 121,
      "cc": 0.9387,
      "no": 11,
      "char_id": "b1c12c11",
      "changed": true
    },
    {
      "x": 2814,
      "y": 2786,
      "w": 197,
      "h": 159,
      "cc": 0.9897,
      "no": 12,
      "char_id": "b1c12c12",
      "changed": true
    },
    {
      "x": 2827,
      "y": 2959,
      "w": 143,
      "h": 136,
      "cc": 0.9579,
      "no": 13,
      "char_id": "b1c12c13",
      "changed": true
    },
    {
      "x": 2789,
      "y": 3109,
      "w": 206,
      "h": 155,
      "cc": 0.8508,
      "no": 14,
      "char_id": "b1c12c14",
      "changed": true
    },
    {
      "x": 2547,
      "y": 894,
      "w": 171,
      "h": 158,
      "cc": 0.9847,
      "no": 1,
      "char_id": "b1c13c1",
      "changed": true
    },
    {
      "x": 2544,
      "y": 1064,
      "w": 195,
      "h": 143,
      "cc": 0.9402,
      "no": 2,
      "char_id": "b1c13c2",
      "changed": true
    },
    {
      "x": 2550,
      "y": 1206,
      "w": 179,
      "h": 136,
      "cc": 0.7495,
      "no": 3,
      "char_id": "b1c13c3",
      "changed": true
    },
    {
      "x": 2556,
      "y": 1360,
      "w": 195,
      "h": 168,
      "cc": 0.8599,
      "no": 4,
      "char_id": "b1c13c4",
      "changed": true
    },
    {
      "x": 2568,
      "y": 1537,
      "w": 160,
      "h": 163,
      "cc": 0.8379,
      "no": 5,
      "char_id": "b1c13c5",
      "changed": true
    },
    {
      "x": 2573,
      "y": 1736,
      "w": 165,
      "h": 132,
      "cc": 0.9343,
      "no": 6,
      "char_id": "b1c13c6",
      "changed": true
    },
    {
      "x": 2559,
      "y": 1907,
      "w": 205,
      "h": 166,
      "cc": 0.9846,
      "no": 7,
      "char_id": "b1c13c7",
      "changed": true
    },
    {
      "x": 2554,
      "y": 2078,
      "w": 212,
      "h": 155,
      "cc": 0.963,
      "no": 8,
      "char_id": "b1c13c8",
      "changed": true
    },
    {
      "x": 2564,
      "y": 2257,
      "w": 190,
      "h": 179,
      "cc": 0.9811,
      "no": 9,
      "char_id": "b1c13c9",
      "changed": true
    },
    {
      "x": 2553,
      "y": 2458,
      "w": 199,
      "h": 150,
      "cc": 0.815,
      "no": 10,
      "char_id": "b1c13c10",
      "changed": true
    },
    {
      "x": 2582,
      "y": 2622,
      "w": 140,
      "h": 147,
      "cc": 0.9228,
      "no": 11,
      "char_id": "b1c13c11",
      "changed": true
    },
    {
      "x": 2582,
      "y": 2782,
      "w": 186,
      "h": 156,
      "cc": 0.9851,
      "no": 12,
      "char_id": "b1c13c12",
      "changed": true
    },
    {
      "x": 2558,
      "y": 2950,
      "w": 178,
      "h": 137,
      "cc": 0.8199,
      "no": 13,
      "char_id": "b1c13c13"
    },
    {
      "x": 2560,
      "y": 3108,
      "w": 184,
      "h": 152,
      "cc": 0.8826,
      "no": 14,
      "char_id": "b1c13c14",
      "changed": true
    },
    {
      "x": 2282,
      "y": 877,
      "w": 222,
      "h": 163,
      "cc": 0.8017,
      "no": 1,
      "char_id": "b1c14c1",
      "changed": true
    },
    {
      "x": 2308,
      "y": 1049,
      "w": 168,
      "h": 112,
      "cc": 0.7396,
      "no": 2,
      "char_id": "b1c14c2",
      "changed": true
    },
    {
      "x": 2285,
      "y": 1179,
      "w": 215,
      "h": 158,
      "cc": 0.6816,
      "no": 3,
      "char_id": "b1c14c3",
      "changed": true
    },
    {
      "x": 2305,
      "y": 1352,
      "w": 202,
      "h": 167,
      "cc": 0.9253,
      "no": 4,
      "char_id": "b1c14c4",
      "changed": true
    },
    {
      "x": 2298,
      "y": 1520,
      "w": 199,
      "h": 172,
      "cc": 0.8089,
      "no": 5,
      "char_id": "b1c14c5",
      "changed": true
    },
    {
      "x": 2318,
      "y": 1711,
      "w": 188,
      "h": 172,
      "cc": 0.9856,
      "no": 6,
      "char_id": "b1c14c6",
      "changed": true
    },
    {
      "x": 2313,
      "y": 1882,
      "w": 207,
      "h": 156,
      "cc": 0.9006,
      "no": 7,
      "char_id": "b1c14c7",
      "changed": true
    },
    {
      "x": 2336,
      "y": 2052,
      "w": 163,
      "h": 161,
      "cc": 0.6835,
      "no": 8,
      "char_id": "b1c14c8",
      "changed": true
    },
    {
      "x": 2301,
      "y": 2217,
      "w": 199,
      "h": 181,
      "cc": 0.692,
      "no": 9,
      "char_id": "b1c14c9",
      "changed": true
    },
    {
      "x": 2314,
      "y": 2410,
      "w": 195,
      "h": 193,
      "cc": 0.9808,
      "no": 10,
      "char_id": "b1c14c10",
      "changed": true
    },
    {
      "x": 2320,
      "y": 2615,
      "w": 175,
      "h": 147,
      "cc": 0.985,
      "no": 11,
      "char_id": "b1c14c11",
      "changed": true
    },
    {
      "x": 2328,
      "y": 2772,
      "w": 171,
      "h": 173,
      "cc": 0.987,
      "no": 12,
      "char_id": "b1c14c12",
      "changed": true
    },
    {
      "x": 2328,
      "y": 2964,
      "w": 187,
      "h": 152,
      "cc": 0.9882,
      "no": 13,
      "char_id": "b1c14c13",
      "changed": true
    },
    {
      "x": 2326,
      "y": 3115,
      "w": 173,
      "h": 150,
      "cc": 0.932,
      "no": 14,
      "char_id": "b1c14c14",
      "changed": true
    },
    {
      "x": 2050,
      "y": 877,
      "w": 179,
      "h": 192,
      "cc": 0.9552,
      "no": 1,
      "char_id": "b1c15c1",
      "changed": true
    },
    {
      "x": 2056,
      "y": 1069,
      "w": 158,
      "h": 147,
      "cc": 0.989,
      "no": 2,
      "char_id": "b1c15c2",
      "changed": true
    },
    {
      "x": 2064,
      "y": 1218,
      "w": 172,
      "h": 149,
      "cc": 0.869,
      "no": 3,
      "char_id": "b1c15c3",
      "changed": true
    },
    {
      "x": 2068,
      "y": 1373,
      "w": 196,
      "h": 193.9,
      "cc": 0.746,
      "no": 4,
      "char_id": "b1c15c4",
      "changed": true
    },
    {
      "x": 2063,
      "y": 1568,
      "w": 178,
      "h": 177,
      "cc": 0.6682,
      "no": 6,
      "char_id": "b1c15c6",
      "changed": true
    },
    {
      "x": 2053,
      "y": 1756,
      "w": 200,
      "h": 157,
      "cc": 0.6535,
      "no": 7,
      "char_id": "b1c15c7",
      "changed": true
    },
    {
      "x": 2044,
      "y": 1914,
      "w": 203,
      "h": 148,
      "cc": 0.9853,
      "no": 8,
      "char_id": "b1c15c8",
      "changed": true
    },
    {
      "x": 2053,
      "y": 2065,
      "w": 190,
      "h": 180,
      "cc": 0.9592,
      "no": 9,
      "char_id": "b1c15c9",
      "changed": true
    },
    {
      "x": 2068,
      "y": 2250,
      "w": 182,
      "h": 162,
      "cc": 0.7609,
      "no": 10,
      "char_id": "b1c15c10",
      "changed": true
    },
    {
      "x": 2060,
      "y": 2416,
      "w": 197,
      "h": 186,
      "cc": 0.8836,
      "no": 11,
      "char_id": "b1c15c11",
      "changed": true
    },
    {
      "x": 2066,
      "y": 2609,
      "w": 177,
      "h": 117,
      "cc": 0.8834,
      "no": 12,
      "char_id": "b1c15c12"
    },
    {
      "x": 2057,
      "y": 2752,
      "w": 188,
      "h": 155,
      "cc": 0.7163,
      "no": 13,
      "char_id": "b1c15c13",
      "changed": true
    },
    {
      "x": 2072,
      "y": 2923,
      "w": 189,
      "h": 132,
      "cc": 0.9008,
      "no": 14,
      "char_id": "b1c15c14",
      "changed": true
    },
    {
      "x": 2083,
      "y": 3080,
      "w": 177,
      "h": 154,
      "cc": 0.9773,
      "no": 15,
      "char_id": "b1c15c15",
      "changed": true
    },
    {
      "x": 1812,
      "y": 881,
      "w": 171,
      "h": 173,
      "cc": 0.9546,
      "no": 1,
      "char_id": "b1c16c1",
      "changed": true
    },
    {
      "x": 1832,
      "y": 1061,
      "w": 148,
      "h": 141,
      "cc": 0.9675,
      "no": 2,
      "char_id": "b1c16c2"
    },
    {
      "x": 1818,
      "y": 1211,
      "w": 179,
      "h": 191,
      "cc": 0.9088,
      "no": 3,
      "char_id": "b1c16c3",
      "changed": true
    },
    {
      "x": 1821,
      "y": 1405,
      "w": 194,
      "h": 153,
      "cc": 0.712,
      "no": 4,
      "char_id": "b1c16c4",
      "changed": true
    },
    {
      "x": 1822,
      "y": 1560,
      "w": 187,
      "h": 178,
      "cc": 0.8797,
      "no": 5,
      "char_id": "b1c16c5",
      "changed": true
    },
    {
      "x": 1827,
      "y": 1740,
      "w": 156,
      "h": 148,
      "cc": 0.9893,
      "no": 6,
      "char_id": "b1c16c6",
      "changed": true
    },
    {
      "x": 1819,
      "y": 1896,
      "w": 181,
      "h": 151,
      "cc": 0.9928,
      "no": 7,
      "char_id": "b1c16c7",
      "changed": true
    },
    {
      "x": 1826,
      "y": 2052,
      "w": 168,
      "h": 172,
      "cc": 0.9815,
      "no": 8,
      "char_id": "b1c16c8",
      "changed": true
    },
    {
      "x": 1836,
      "y": 2228,
      "w": 134,
      "h": 164,
      "cc": 0.8897,
      "no": 9,
      "char_id": "b1c16c9",
      "changed": true
    },
    {
      "x": 1815,
      "y": 2399,
      "w": 207,
      "h": 164,
      "cc": 0.8552,
      "no": 10,
      "char_id": "b1c16c10",
      "changed": true
    },
    {
      "x": 1814,
      "y": 2585,
      "w": 187,
      "h": 172,
      "cc": 0.9657,
      "no": 11,
      "char_id": "b1c16c11",
      "changed": true
    },
    {
      "x": 1835,
      "y": 2762,
      "w": 180,
      "h": 154,
      "cc": 0.9228,
      "no": 12,
      "char_id": "b1c16c12",
      "changed": true
    },
    {
      "x": 1818,
      "y": 2930,
      "w": 209,
      "h": 186,
      "cc": 0.9725,
      "no": 13,
      "char_id": "b1c16c13",
      "changed": true
    },
    {
      "x": 1835,
      "y": 3119,
      "w": 173,
      "h": 145,
      "cc": 0.8188,
      "no": 14,
      "char_id": "b1c16c14",
      "changed": true
    },
    {
      "x": 1588,
      "y": 872,
      "w": 153,
      "h": 214,
      "cc": 0.9545,
      "no": 1,
      "char_id": "b1c17c1",
      "changed": true
    },
    {
      "x": 1590,
      "y": 1088,
      "w": 194,
      "h": 141,
      "cc": 0.9764,
      "no": 2,
      "char_id": "b1c17c2",
      "changed": true
    },
    {
      "x": 1577,
      "y": 1230,
      "w": 184,
      "h": 207,
      "cc": 0.9726,
      "no": 3,
      "char_id": "b1c17c3",
      "changed": true
    },
    {
      "x": 1582,
      "y": 1443,
      "w": 168,
      "h": 111,
      "cc": 0.9864,
      "no": 4,
      "char_id": "b1c17c4",
      "changed": true
    },
    {
      "x": 1582,
      "y": 1553,
      "w": 193,
      "h": 163,
      "cc": 0.9976,
      "no": 5,
      "char_id": "b1c17c5",
      "changed": true
    },
    {
      "x": 1580,
      "y": 1724,
      "w": 168,
      "h": 152,
      "cc": 0.9899,
      "no": 6,
      "char_id": "b1c17c6",
      "changed": true
    },
    {
      "x": 1572,
      "y": 1883,
      "w": 204,
      "h": 166,
      "cc": 0.9855,
      "no": 7,
      "char_id": "b1c17c7",
      "changed": true
    },
    {
      "x": 1574,
      "y": 2078,
      "w": 183,
      "h": 143,
      "cc": 0.969,
      "no": 8,
      "char_id": "b1c17c8",
      "changed": true
    },
    {
      "x": 1597,
      "y": 2251,
      "w": 145,
      "h": 134,
      "cc": 0.975,
      "no": 9,
      "char_id": "b1c17c9",
      "changed": true
    },
    {
      "x": 1586,
      "y": 2406,
      "w": 177,
      "h": 160,
      "cc": 0.6333,
      "no": 10,
      "char_id": "b1c17c10",
      "changed": true
    },
    {
      "x": 1574,
      "y": 2576,
      "w": 182,
      "h": 176,
      "cc": 0.7346,
      "no": 11,
      "char_id": "b1c17c11",
      "changed": true
    },
    {
      "x": 1297,
      "y": 866,
      "w": 215,
      "h": 182,
      "cc": 0.9475,
      "no": 1,
      "char_id": "b1c18c1",
      "changed": true
    },
    {
      "x": 1316,
      "y": 1051,
      "w": 205,
      "h": 164,
      "cc": 0.9324,
      "no": 2,
      "char_id": "b1c18c2",
      "changed": true
    },
    {
      "x": 1316,
      "y": 1223,
      "w": 180,
      "h": 153,
      "cc": 0.8823,
      "no": 3,
      "char_id": "b1c18c3",
      "changed": true
    },
    {
      "x": 1312,
      "y": 1385,
      "w": 222,
      "h": 180,
      "cc": 0.9125,
      "no": 4,
      "char_id": "b1c18c4",
      "changed": true
    },
    {
      "x": 1311,
      "y": 1570,
      "w": 228,
      "h": 174,
      "cc": 0.6209,
      "no": 5,
      "char_id": "b1c18c5",
      "changed": true
    },
    {
      "x": 1331,
      "y": 1755,
      "w": 194,
      "h": 126,
      "cc": 0.956,
      "no": 6,
      "char_id": "b1c18c6",
      "changed": true
    },
    {
      "x": 1318,
      "y": 1887,
      "w": 203,
      "h": 105,
      "cc": 0.9494,
      "no": 7,
      "char_id": "b1c18c7"
    },
    {
      "x": 1330,
      "y": 2017,
      "w": 164,
      "h": 188,
      "cc": 0.9488,
      "no": 8,
      "char_id": "b1c18c8",
      "changed": true
    },
    {
      "x": 1340,
      "y": 2204,
      "w": 148,
      "h": 100,
      "cc": 0.9635,
      "no": 9,
      "char_id": "b1c18c9"
    },
    {
      "x": 1342,
      "y": 2319,
      "w": 159,
      "h": 138,
      "cc": 0.9912,
      "no": 10,
      "char_id": "b1c18c10",
      "changed": true
    },
    {
      "x": 1325,
      "y": 2495,
      "w": 193,
      "h": 80,
      "cc": 0.8965,
      "no": 11,
      "char_id": "b1c18c11",
      "changed": true
    },
    {
      "x": 1351,
      "y": 2638,
      "w": 142,
      "h": 131,
      "cc": 0.9546,
      "no": 12,
      "char_id": "b1c18c12"
    },
    {
      "x": 1327,
      "y": 2797,
      "w": 173,
      "h": 145,
      "cc": 0.9885,
      "no": 13,
      "char_id": "b1c18c13",
      "changed": true
    },
    {
      "x": 1335,
      "y": 2965,
      "w": 166,
      "h": 138,
      "cc": 0.9607,
      "no": 14,
      "char_id": "b1c18c14"
    },
    {
      "x": 1313,
      "y": 3143,
      "w": 210,
      "h": 114,
      "cc": 0.9289,
      "no": 15,
      "char_id": "b1c18c15",
      "changed": true
    },
    {
      "x": 1068,
      "y": 892,
      "w": 161,
      "h": 112,
      "cc": 0.8573,
      "no": 1,
      "char_id": "b1c19c1",
      "changed": true
    },
    {
      "x": 1045,
      "y": 1022,
      "w": 219,
      "h": 183,
      "cc": 0.959,
      "no": 2,
      "char_id": "b1c19c2",
      "changed": true
    },
    {
      "x": 1078,
      "y": 1205,
      "w": 157,
      "h": 137,
      "cc": 0.9676,
      "no": 3,
      "char_id": "b1c19c3",
      "changed": true
    },
    {
      "x": 1056,
      "y": 1357,
      "w": 188,
      "h": 154,
      "cc": 0.9889,
      "no": 4,
      "char_id": "b1c19c4",
      "changed": true
    },
    {
      "x": 1057,
      "y": 1515,
      "w": 201,
      "h": 171,
      "cc": 0.7977,
      "no": 5,
      "char_id": "b1c19c5",
      "changed": true
    },
    {
      "x": 1063,
      "y": 1687,
      "w": 184,
      "h": 209,
      "cc": 0.9595,
      "no": 6,
      "char_id": "b1c19c6",
      "changed": true
    },
    {
      "x": 1036,
      "y": 1945,
      "w": 127,
      "h": 108,
      "cc": 0.7762,
      "no": 7,
      "char_id": "b1c19c7",
      "changed": true
    },
    {
      "x": 1164,
      "y": 1938,
      "w": 100,
      "h": 108,
      "cc": 0.6892,
      "no": 8,
      "char_id": "b1c19c8",
      "changed": true
    },
    {
      "x": 1169,
      "y": 2058,
      "w": 100,
      "h": 75,
      "cc": 0.8299,
      "no": 9,
      "char_id": "b1c19c9",
      "changed": true
    },
    {
      "x": 1034,
      "y": 2074,
      "w": 134,
      "h": 110,
      "cc": 0.7869,
      "no": 10,
      "char_id": "b1c19c10",
      "changed": true
    },
    {
      "x": 1172,
      "y": 2135,
      "w": 98,
      "h": 78,
      "cc": 0.8668,
      "no": 11,
      "char_id": "b1c19c11",
      "changed": true
    },
    {
      "x": 1052,
      "y": 2194,
      "w": 116,
      "h": 66,
      "cc": 0.9457,
      "no": 13,
      "char_id": "b1c19c13",
      "changed": true
    },
    {
      "x": 1171,
      "y": 2241,
      "w": 104,
      "h": 78,
      "cc": 0.762,
      "no": 15,
      "char_id": "b1c19c15",
      "changed": true
    },
    {
      "x": 1050,
      "y": 2271,
      "w": 119,
      "h": 134,
      "cc": 0.9591,
      "no": 16,
      "char_id": "b1c19c16",
      "changed": true
    },
    {
      "x": 1168,
      "y": 2345,
      "w": 107,
      "h": 78,
      "cc": 0.9516,
      "no": 17,
      "char_id": "b1c19c17",
      "changed": true
    },
    {
      "x": 1058,
      "y": 2435,
      "w": 101,
      "h": 69,
      "cc": 0.9601,
      "no": 18,
      "char_id": "b1c19c18"
    },
    {
      "x": 1164,
      "y": 2444,
      "w": 118,
      "h": 118,
      "cc": 0.9578,
      "no": 19,
      "char_id": "b1c19c19",
      "changed": true
    },
    {
      "x": 1041,
      "y": 2528,
      "w": 119,
      "h": 101,
      "cc": 0.8644,
      "no": 20,
      "char_id": "b1c19c20",
      "changed": true
    },
    {
      "x": 1170,
      "y": 2579,
      "w": 127,
      "h": 115,
      "cc": 0.7817,
      "no": 21,
      "char_id": "b1c19c21",
      "changed": true
    },
    {
      "x": 1043,
      "y": 2650,
      "w": 118,
      "h": 66,
      "cc": 0.9276,
      "no": 22,
      "char_id": "b1c19c22",
      "changed": true
    },
    {
      "x": 1178,
      "y": 2715,
      "w": 93,
      "h": 83,
      "cc": 0.9476,
      "no": 23,
      "char_id": "b1c19c23",
      "changed": true
    },
    {
      "x": 1055,
      "y": 2746,
      "w": 94,
      "h": 93,
      "cc": 0.9307,
      "no": 24,
      "char_id": "b1c19c24",
      "changed": true
    },
    {
      "x": 1179,
      "y": 2827,
      "w": 103,
      "h": 87,
      "cc": 0.7299,
      "no": 25,
      "char_id": "b1c19c25",
      "changed": true
    },
    {
      "x": 1043,
      "y": 2859,
      "w": 122,
      "h": 42,
      "cc": 0.9203,
      "no": 26,
      "char_id": "b1c19c26",
      "changed": true
    },
    {
      "x": 1050,
      "y": 2925,
      "w": 112,
      "h": 95,
      "cc": 0.9667,
      "no": 28,
      "char_id": "b1c19c28",
      "changed": true
    },
    {
      "x": 1165,
      "y": 2930,
      "w": 117,
      "h": 102,
      "cc": 0.963,
      "no": 29,
      "char_id": "b1c19c29",
      "changed": true
    },
    {
      "x": 1170,
      "y": 3038,
      "w": 99,
      "h": 82,
      "cc": 0.9696,
      "no": 30,
      "char_id": "b1c19c30",
      "changed": true
    },
    {
      "x": 1042,
      "y": 3043,
      "w": 125,
      "h": 88,
      "cc": 0.9471,
      "no": 31,
      "char_id": "b1c19c31",
      "changed": true
    },
    {
      "x": 1166,
      "y": 3125,
      "w": 130,
      "h": 117,
      "cc": 0.9405,
      "no": 33,
      "char_id": "b1c19c33",
      "changed": true
    },
    {
      "x": 1039,
      "y": 3148,
      "w": 121,
      "h": 95,
      "cc": 0.6736,
      "no": 34,
      "char_id": "b1c19c34",
      "changed": true
    },
    {
      "x": 794,
      "y": 868,
      "w": 119,
      "h": 137,
      "cc": 0.9022,
      "no": 1,
      "char_id": "b1c20c1",
      "changed": true
    },
    {
      "x": 913,
      "y": 871,
      "w": 105,
      "h": 126,
      "cc": 0.8725,
      "no": 2,
      "char_id": "b1c20c2",
      "changed": true
    },
    {
      "x": 803,
      "y": 1021,
      "w": 102,
      "h": 102,
      "cc": 0.9515,
      "no": 3,
      "char_id": "b1c20c3",
      "changed": true
    },
    {
      "x": 908,
      "y": 1023,
      "w": 102,
      "h": 97,
      "cc": 0.9079,
      "no": 4,
      "char_id": "b1c20c4",
      "changed": true
    },
    {
      "x": 807,
      "y": 1126,
      "w": 93,
      "h": 90,
      "cc": 0.9504,
      "no": 5,
      "char_id": "b1c20c5",
      "changed": true
    },
    {
      "x": 905,
      "y": 1131,
      "w": 105,
      "h": 102,
      "cc": 0.8582,
      "no": 6,
      "char_id": "b1c20c6",
      "changed": true
    },
    {
      "x": 808,
      "y": 1236,
      "w": 95,
      "h": 130,
      "cc": 0.7205,
      "no": 7,
      "char_id": "b1c20c7",
      "changed": true
    },
    {
      "x": 905,
      "y": 1240,
      "w": 132,
      "h": 133,
      "cc": 0.7288,
      "no": 8,
      "char_id": "b1c20c8",
      "changed": true
    },
    {
      "x": 586,
      "y": 1041,
      "w": 164,
      "h": 179,
      "cc": 0.7678,
      "no": 1,
      "char_id": "b1c21c1"
    },
    {
      "x": 564,
      "y": 1237,
      "w": 199,
      "h": 154,
      "cc": 0.7204,
      "no": 2,
      "char_id": "b1c21c2",
      "changed": true
    },
    {
      "x": 594,
      "y": 1418,
      "w": 165,
      "h": 154,
      "cc": 0.937,
      "no": 3,
      "char_id": "b1c21c3",
      "changed": true
    },
    {
      "x": 592,
      "y": 1587,
      "w": 170,
      "h": 155,
      "cc": 0.8714,
      "no": 4,
      "char_id": "b1c21c4",
      "changed": true
    },
    {
      "x": 568,
      "y": 1747,
      "w": 192,
      "h": 165,
      "cc": 0.8787,
      "no": 5,
      "char_id": "b1c21c5",
      "changed": true
    },
    {
      "x": 582,
      "y": 1926,
      "w": 165,
      "h": 129,
      "cc": 0.6934,
      "no": 6,
      "char_id": "b1c21c6",
      "changed": true
    },
    {
      "x": 572,
      "y": 2083,
      "w": 177,
      "h": 172,
      "cc": 0.9354,
      "no": 7,
      "char_id": "b1c21c7",
      "changed": true
    },
    {
      "x": 587,
      "y": 2283,
      "w": 157,
      "h": 103,
      "cc": 0.7487,
      "no": 8,
      "char_id": "b1c21c8",
      "changed": true
    },
    {
      "x": 582,
      "y": 2403,
      "w": 174,
      "h": 151,
      "cc": 0.7397,
      "no": 9,
      "char_id": "b1c21c9",
      "changed": true
    },
    {
      "x": 319,
      "y": 1006,
      "w": 173,
      "h": 143,
      "cc": 0.9307,
      "no": 1,
      "char_id": "b1c22c1",
      "changed": true
    },
    {
      "x": 337,
      "y": 1163,
      "w": 179,
      "h": 187,
      "cc": 0.9014,
      "no": 2,
      "char_id": "b1c22c2",
      "changed": true
    },
    {
      "x": 324,
      "y": 1350,
      "w": 228,
      "h": 175,
      "cc": 0.9677,
      "no": 3,
      "char_id": "b1c22c3",
      "changed": true
    },
    {
      "x": 434,
      "y": 1537,
      "w": 106,
      "h": 100,
      "cc": 0.695,
      "no": 4,
      "char_id": "b1c22c4",
      "changed": true
    },
    {
      "x": 318,
      "y": 1548,
      "w": 117,
      "h": 105,
      "cc": 0.7756,
      "no": 5,
      "char_id": "b1c22c5",
      "changed": true
    },
    {
      "x": 434,
      "y": 1650,
      "w": 111,
      "h": 106,
      "cc": 0.8216,
      "no": 6,
      "char_id": "b1c22c6",
      "changed": true
    },
    {
      "x": 433,
      "y": 1757,
      "w": 91,
      "h": 86,
      "cc": 0.8054,
      "no": 7,
      "char_id": "b1c22c7",
      "changed": true
    },
    {
      "x": 330,
      "y": 1782,
      "w": 99,
      "h": 121,
      "cc": 0.6923,
      "no": 8,
      "char_id": "b1c22c8",
      "changed": true
    },
    {
      "x": 439,
      "y": 1850,
      "w": 76,
      "h": 93,
      "cc": 0.8523,
      "no": 9,
      "char_id": "b1c22c9"
    },
    {
      "x": 319,
      "y": 1906,
      "w": 107,
      "h": 125,
      "cc": 0.9566,
      "no": 10,
      "char_id": "b1c22c10",
      "changed": true
    },
    {
      "x": 428,
      "y": 1957,
      "w": 107,
      "h": 126,
      "cc": 0.9111,
      "no": 11,
      "char_id": "b1c22c11",
      "changed": true
    },
    {
      "x": 300,
      "y": 2048,
      "w": 123,
      "h": 116,
      "cc": 0.9309,
      "no": 12,
      "char_id": "b1c22c12",
      "changed": true
    },
    {
      "x": 426,
      "y": 2084,
      "w": 97,
      "h": 107,
      "cc": 0.9184,
      "no": 13,
      "char_id": "b1c22c13",
      "changed": true
    },
    {
      "x": 333,
      "y": 2246,
      "w": 180,
      "h": 72,
      "cc": 0.6353,
      "no": 14,
      "char_id": "b1c22c14",
      "changed": true
    },
    {
      "x": 325,
      "y": 2318,
      "w": 154,
      "h": 126,
      "cc": 0.8938,
      "no": 15,
      "char_id": "b1c22c15",
      "changed": true
    },
    {
      "x": 375,
      "y": 2453,
      "w": 104,
      "h": 120,
      "cc": 0.7595,
      "no": 16,
      "char_id": "b1c22c16",
      "changed": true
    },
    {
      "x": 346,
      "y": 2577,
      "w": 183,
      "h": 155,
      "cc": 0.7829,
      "no": 17,
      "char_id": "b1c22c17",
      "changed": true
    },
    {
      "x": 423,
      "y": 2734,
      "w": 97,
      "h": 69,
      "cc": 0.8324,
      "no": 18,
      "char_id": "b1c22c18"
    },
    {
      "x": 311,
      "y": 2741,
      "w": 110,
      "h": 111,
      "cc": 0.9195,
      "no": 19,
      "char_id": "b1c22c19"
    },
    {
      "x": 423,
      "y": 2805,
      "w": 98,
      "h": 51,
      "cc": 0.7498,
      "no": 20,
      "char_id": "b1c22c20",
      "changed": true
    },
    {
      "x": 318,
      "y": 2862,
      "w": 82,
      "h": 54,
      "cc": 0.7315,
      "no": 22,
      "char_id": "b1c22c22"
    },
    {
      "x": 319,
      "y": 2932,
      "w": 80,
      "h": 69,
      "cc": 0.9119,
      "no": 24,
      "char_id": "b1c22c24"
    },
    {
      "x": 410,
      "y": 2979,
      "w": 121,
      "h": 80,
      "cc": 0.6865,
      "no": 25,
      "char_id": "b1c22c25",
      "changed": true
    },
    {
      "x": 312,
      "y": 3011,
      "w": 93,
      "h": 120,
      "cc": 0.7697,
      "no": 26,
      "char_id": "b1c22c26",
      "changed": true
    },
    {
      "x": 409,
      "y": 3066,
      "w": 130,
      "h": 106,
      "cc": 0.9411,
      "no": 27,
      "char_id": "b1c22c27",
      "changed": true
    },
    {
      "x": 294,
      "y": 3140,
      "w": 111,
      "h": 115,
      "cc": 0.7135,
      "no": 28,
      "char_id": "b1c22c28"
    },
    {
      "x": 95,
      "y": 932,
      "w": 176,
      "h": 126,
      "cc": 0.9415,
      "no": 1,
      "char_id": "b1c23c1",
      "changed": true
    },
    {
      "x": 92,
      "y": 1077,
      "w": 151,
      "h": 144,
      "cc": 0.973,
      "no": 2,
      "char_id": "b1c23c2",
      "changed": true
    },
    {
      "x": 95,
      "y": 1253,
      "w": 185,
      "h": 169,
      "cc": 0.9837,
      "no": 3,
      "char_id": "b1c23c3",
      "changed": true
    },
    {
      "x": 76,
      "y": 1427,
      "w": 211,
      "h": 172,
      "cc": 0.9834,
      "no": 4,
      "char_id": "b1c23c4",
      "changed": true
    },
    {
      "x": 108,
      "y": 2234,
      "w": 142,
      "h": 106,
      "cc": 0.9569,
      "no": 5,
      "char_id": "b1c23c5",
      "changed": true
    },
    {
      "x": 86,
      "y": 2350,
      "w": 150,
      "h": 132,
      "cc": 0.9764,
      "no": 6,
      "char_id": "b1c23c6",
      "changed": true
    },
    {
      "x": 100,
      "y": 2492,
      "w": 142,
      "h": 116,
      "cc": 0.9547,
      "no": 7,
      "char_id": "b1c23c7",
      "changed": true
    },
    {
      "x": 85,
      "y": 2608,
      "w": 203,
      "h": 170,
      "cc": 0.9921,
      "no": 8,
      "char_id": "b1c23c8",
      "changed": true
    },
    {
      "x": 73,
      "y": 2789,
      "w": 216,
      "h": 144,
      "cc": 0.9881,
      "no": 9,
      "char_id": "b1c23c9",
      "changed": true
    },
    {
      "x": 72,
      "y": 2961,
      "w": 97,
      "h": 107,
      "cc": 0.6516,
      "no": 10,
      "char_id": "b1c23c10",
      "changed": true
    },
    {
      "x": 171,
      "y": 2973,
      "w": 111,
      "h": 102,
      "cc": 0.8458,
      "no": 11,
      "char_id": "b1c23c11",
      "changed": true
    },
    {
      "x": 184,
      "y": 3080,
      "w": 82,
      "h": 89,
      "cc": 0.8426,
      "no": 12,
      "char_id": "b1c23c12",
      "changed": true
    },
    {
      "x": 59,
      "y": 3069,
      "w": 108,
      "h": 78,
      "cc": 0.9194,
      "no": 13,
      "char_id": "b1c23c13",
      "changed": true
    },
    {
      "char_id": "new2",
      "changed": true,
      "x": 5322.1,
      "y": 2368.1,
      "w": 127.8,
      "h": 107.8
    },
    {
      "char_id": "new3",
      "changed": true,
      "x": 4964.7,
      "y": 2372,
      "w": 112.8,
      "h": 111.8
    },
    {
      "char_id": "new4",
      "x": 576,
      "y": 875.5,
      "w": 191.7,
      "h": 154.7
    },
    {
      "char_id": "new5",
      "x": 349.4,
      "y": 946.4,
      "w": 185.7,
      "h": 47.9
    },
    {
      "char_id": "new6",
      "changed": true,
      "x": 301.5,
      "y": 1659.2,
      "w": 130.8,
      "h": 107.8
    },
    {
      "char_id": "new7",
      "changed": true,
      "x": 411.3,
      "y": 2862.2,
      "w": 131.8,
      "h": 113.8
    },
    {
      "char_id": "new8",
      "changed": true,
      "x": 403.3,
      "y": 3170.7,
      "w": 145.8,
      "h": 101.8
    }
  ]
}